sia/__init__.py
sia/els_core.py
sia/els_parser.py
sia/hdqs.py
sia/ntt.py
sia_script-0.6.4.dist-info/licenses/LICENSE.md
sia_script-0.6.4.dist-info/METADATA
sia_script-0.6.4.dist-info/WHEEL
sia_script-0.6.4.dist-info/top_level.txt
sia_script-0.6.4.dist-info/RECORD
