Metadata-Version: 2.4
Name: sia-script
Version: 0.6.4
Summary: SIA — Simplified Integrated Architecture including SiaNTT, SIA-ELS (ABAP Interpreter), and HDQS (Hyper-Dimensional Quantum System)
Author-email: Sia Software Innovations Private Limited <info@siasoftwareinnovations.com>
License: # PROPRIETARY SOFTWARE LICENSE
Project-URL: Homepage, https://www.siasoftwareinnovations.com
Project-URL: Documentation, https://www.siasoftwareinnovations.com
Keywords: SIA,Python,Interpreter,ABAP,Enterprise Logic Studio,Quantum,HDQS,Quantum Computing,Quantum Machine Learning,Hyper-Dimensional Quantum System,OOP,SiaML,SiaNTT
Classifier: Programming Language :: Python :: 3
Classifier: Programming Language :: Python :: 3.8
Classifier: Programming Language :: Python :: 3.9
Classifier: Programming Language :: Python :: 3.10
Classifier: Programming Language :: Python :: 3.11
Classifier: Programming Language :: Python :: 3.12
Classifier: Operating System :: OS Independent
Classifier: Topic :: Software Development :: Interpreters
Classifier: Topic :: Scientific/Engineering :: Artificial Intelligence
Classifier: Topic :: Scientific/Engineering :: Quantum Computing
Classifier: Topic :: Software Development :: Libraries :: Python Modules
Classifier: Topic :: System :: Distributed Computing
Requires-Python: >=3.8
License-File: LICENSE.md
Provides-Extra: full
Requires-Dist: numpy>=1.24.0; extra == "full"
Requires-Dist: scipy>=1.11.0; extra == "full"
Requires-Dist: matplotlib>=3.7.0; extra == "full"
Requires-Dist: requests>=2.31.0; extra == "full"
Requires-Dist: fastapi>=0.104.0; extra == "full"
Requires-Dist: uvicorn>=0.24.0; extra == "full"
Requires-Dist: pydantic>=2.4.0; extra == "full"
Requires-Dist: psutil>=5.9.0; extra == "full"
Provides-Extra: quantum
Requires-Dist: numpy>=1.24.0; extra == "quantum"
Requires-Dist: scipy>=1.11.0; extra == "quantum"
Requires-Dist: requests>=2.31.0; extra == "quantum"
Provides-Extra: server
Requires-Dist: fastapi>=0.104.0; extra == "server"
Requires-Dist: uvicorn>=0.24.0; extra == "server"
Requires-Dist: pydantic>=2.4.0; extra == "server"
Requires-Dist: psutil>=5.9.0; extra == "server"
Dynamic: license-file
